nonebot_plugin_penguin/__init__.py
nonebot_plugin_penguin/config.py
nonebot_plugin_penguin/db.py
nonebot_plugin_penguin/render/__init__.py
nonebot_plugin_penguin/render/item_sprite.py
nonebot_plugin_penguin/render/table.py
nonebot_plugin_penguin/render/templates/app.css
nonebot_plugin_penguin/render/templates/card.css
nonebot_plugin_penguin/render/templates/item_card.html
nonebot_plugin_penguin/render/templates/sprite.202210111514.png
nonebot_plugin_penguin/render/templates/stage_card.html
nonebot_plugin_penguin/render/utils.py
nonebot_plugin_penguin/request.py
nonebot_plugin_penguin/schedule.py
nonebot_plugin_penguin/startup.py
nonebot_plugin_penguin/trim.py
nonebot_plugin_penguin/types.py
nonebot_plugin_penguin/user.py
nonebot_plugin_penguin/utils.py
nonebot_plugin_penguin-0.1.0.dist-info/LICENSE
nonebot_plugin_penguin-0.1.0.dist-info/METADATA
nonebot_plugin_penguin-0.1.0.dist-info/WHEEL
nonebot_plugin_penguin-0.1.0.dist-info/RECORD
