Metadata-Version: 2.1
Name: nonebot-plugin-penguin
Version: 0.1.0
Summary: get penguin data and send from https://penguin-stats.io/
Home-page: https://github.com/AzideCupric/nonebot-plugin-penguin
License: MIT
Author: Azide
Author-email: rukuy@qq.com
Requires-Python: >=3.10,<4.0
Classifier: Development Status :: 3 - Alpha
Classifier: License :: OSI Approved :: MIT License
Classifier: Operating System :: Microsoft :: Windows
Classifier: Operating System :: POSIX :: Linux
Classifier: Programming Language :: Python :: 3
Classifier: Programming Language :: Python :: 3.10
Classifier: Programming Language :: Python :: 3.11
Requires-Dist: httpx (>=0.23.3,<0.25.0)
Requires-Dist: nonebot-adapter-onebot (>=2.2.2,<3.0.0)
Requires-Dist: nonebot-plugin-apscheduler (>=0.2.0,<0.3.0)
Requires-Dist: nonebot-plugin-htmlrender (>=0.2.0.3,<0.3.0.0)
Requires-Dist: nonebot-plugin-send-anything-anywhere (>=0.2.2,<0.3.0)
Requires-Dist: nonebot2[fastapi] (>=2.0.0,<3.0.0)
Requires-Dist: tinydb (>=4.7.1,<5.0.0)
Project-URL: Repository, https://github.com/AzideCupric/nonebot-plugin-penguin
